[
  {
    "applies_to":["EN_background_check"],
    "qctests":["EN_spike_and_step_check"],
    "data":["EN_bgcheck_info.nc"]
  },
  {
    "applies_to":["EN_background_available_check"],
    "qctests":["EN_background_check"]
  },
  { "applies_to":["EN_increasing_depth_check"],
    "qctests":["EN_spike_and_step_check"]
  },
  {
    "applies_to":["CoTeDe_*"],
    "modules":["cotede"]
  },
  {
    "applies_to":["CoTeDe_Argo_density_inversion"],
    "modules":["gsw"]
  },
  {
    "applies_to":["CoTeDe_WOA_normbias"],
    "data":["temperature_seasonal_5deg.nc"]
  },
  {
    "applies_to":["CoTeDe_location_at_sea_test"],
    "data":["etopo5.nc"]
  },
  {
    "applies_to":["CoTeDe_fuzzy_logic"],
    "modules":["skfuzzy"],
    "data":["temperature_seasonal_5deg.nc"]
  }
]
 


